{
  "Ca_o": 2,
  "Cm": 9.5e-05,
  "Cmdn_tot": 0.02,
  "F": 96485.3415,
  "K_leak_rate": 0,
  "K_mK": 1,
  "K_mNa": 21.7,
  "K_mk1": 10,
  "K_o": 4,
  "K_rel_max": 500,
  "Na_o": 140,
  "P_Ca_L_Ca": 0.25,
  "R": 8314.472,
  "SL": 2.15,
  "T": 310,
  "Tau_CaMK": 0.8,
  "Tau_SRCa_RyR": 0.05,
  "Trpn_tot": 0.07,
  "V_max_f": 0.292,
  "V_max_r": 0.391,
  "alpha_cmdn": 10000,
  "alpha_trpn": 80000,
  "beta_cmdn": 500,
  "beta_tm": 40,
  "beta_trpn": 200,
  "delta_m": 1e-05,
  "f_XB": 10,
  "g_K1": 1,
  "g_Na": 2.5,
  "g_XB": 30,
  "g_b_Ca": 0.00025,
  "g_b_K": 0.0006,
  "g_b_Na": 0.0006,
  "g_to": 0.005,
  "gain_k1": 1,
  "gain_k2": 1,
  "gain_k3": 1,
  "gain_k4": 1,
  "gamma": 0.5,
  "i_Kmax": 1,
  "i_NaCa_max": 0.0005,
  "i_NaK_max": 1.36,
  "shift_h": 0,
  "speed_d": 3,
  "speed_f": 0.5,
  "stim_amplitude": -4,
  "stim_duration": 0.002,
  "stim_end": 1000,
  "stim_period": 0.5,
  "stim_start": 0,
  "v_SR": 3.3477e-06,
  "v_i": 1.6404e-05,
  "zeta": 0.1
}